{
  "feature": "HODGE-346",
  "type": "epic",
  "stories": [
    {
      "id": "HODGE-346.1",
      "title": "Standards validation and review profile creation",
      "description": "Validate UX design against existing docs + create enforcing review profile that can lint slash command files",
      "effort": "small",
      "dependencies": [],
      "lane": 0
    },
    {
      "id": "HODGE-346.2",
      "title": "Core visual language patterns (interaction starts, response indicators)",
      "description": "Update all 10 command files with consistent interaction starts (box pattern) and response indicators (🔔 YOUR RESPONSE NEEDED)",
      "effort": "medium",
      "dependencies": ["HODGE-346.1"],
      "lane": 0
    },
    {
      "id": "HODGE-346.3",
      "title": "Choice formatting and recommendations (alphabetized lists, ⭐ marking)",
      "description": "Standardize all option lists to alphabetized format (a/b/c/d) with clear recommendation marking using ⭐ emoji",
      "effort": "medium",
      "dependencies": ["HODGE-346.2"],
      "lane": 0
    },
    {
      "id": "HODGE-346.4",
      "title": "Next steps formatting (bulleted slash commands, context-aware filtering)",
      "description": "Standardize What's Next sections with bulleted slash commands and implement smart command filtering based on project state",
      "effort": "medium",
      "dependencies": ["HODGE-346.3"],
      "lane": 0
    },
    {
      "id": "HODGE-346.5",
      "title": "Tone and personality refinement (knowledgeable peer, error recovery)",
      "description": "Update all text to knowledgeable peer tone and add collaborative error recovery hints throughout commands",
      "effort": "medium",
      "dependencies": ["HODGE-346.4"],
      "lane": 0
    }
  ],
  "lanes": {
    "count": 1,
    "assignments": {
      "0": ["HODGE-346.1", "HODGE-346.2", "HODGE-346.3", "HODGE-346.4", "HODGE-346.5"]
    }
  },
  "dependencies": {
    "HODGE-346.2": ["HODGE-346.1"],
    "HODGE-346.3": ["HODGE-346.2"],
    "HODGE-346.4": ["HODGE-346.3"],
    "HODGE-346.5": ["HODGE-346.4"]
  },
  "estimatedDays": 9,
  "createdAt": "2025-10-16T05:30:00.000Z"
}
